{
    "id": 105,
    "title": "Interactive video Wall",
    "isAutopalySlide": true,
    "slides": [{
        "id": 100,
        "src": "i/slides/interactiveVid0.jpg"
    }, {
        "id": 101,
        "src": "i/slides/interactiveVid1.jpg"
    }, {
        "id": 102,
        "src": "i/slides/interactiveVid2.jpg"
    }, {
        "id": 103,
        "src": "i/slides/interactiveVid3.jpg"
    }, {
        "id": 104,
        "src": "i/slides/interactiveVid4.jpg"
    }],
    "content": "<section class='excerpt'><h3 class='que'>How does Cardinal Health partner with customers?</h3> <div class='ans'>Lorem ipsum dolor sit amet, consectetur adipisicing elit, sed do eiusmod tempor incididunt ut labore et dolore..</div></section>"
    
}
